Lab 5 - Building a Simple Processor/Part 3 - Integration & Control/control_unit.v
// Computer Architecture (CO224) - Lab 05
// Design: Control Unit for Integrated CPU module
// Author: Group 27
// Members: E/18/077 Nipun Dharmarathne
// 			E/18/227 Dinuka Mudalige
// Date: 20/01/2022

module control_unit (
	input[7:0] OPCODE, 
	output[2:0] ALUOP, 
	output WRITEENABLE, 
	output MUXCOMP, 
	output MUXIMM);
	// Here, 
	// MUXCOMP --> Multiplexer associate with 2's Complement Operation
	// MUXIMM --> Multiplexer associate with IMMEDIATE
	reg WRITEENABLE, MUXCOMP, MUXIMM;
	reg[2:0] ALUOP;

always @(OPCODE) begin
	//decoding the opcodes
	case(OPCODE)
		8'b00000000: begin			// op_loadi
				ALUOP = 3'b000;
				MUXCOMP = 1'b0;
				MUXIMM = 1'b1;
				WRITEENABLE = 1'b1;
			end

		8'b00000001: begin			// op_mov
				ALUOP = 3'b000;
				MUXCOMP = 1'b0;
				MUXIMM = 1'b1;
				WRITEENABLE = 1'b1;  
			end

		8'b00000010: begin			// op_add
				ALUOP = 3'b001;
				MUXCOMP = 1'b0;
				MUXIMM = 1'b1;
				WRITEENABLE = 1'b1;
			end

		8'b00000011: begin			// op_sub
				ALUOP = 3'b001;
				MUXCOMP = 1'b0;
				MUXIMM = 1'b0;
				WRITEENABLE = 1'b1;
			end

		8'b00000100: begin			// op_and
				ALUOP = 3'b010;
				MUXCOMP = 1'b0;
				MUXIMM = 1'b1;
				WRITEENABLE = 1'b1;
			end

		8'b00000101: begin			// op_or
				ALUOP = 3'b011;
				MUXCOMP = 1'b0;
				MUXIMM = 1'b1;
				WRITEENABLE = 1'b1;
			end

        default: begin
            MUXCOMP = 1'b0; 	// Disabling the output for a sub instruction
            MUXIMM = 1'b0; 	// Disabling the trigger for an immediate value
            WRITEENABLE = 1'b0; 	// Disabling the written enable signal
            end			     
	endcase        
	end
	
endmodule

Lab 5 - Building a Simple Processor/Part 3 - Integration & Control/alu.v
// Computer Architecture (CO224) - Lab 05 - Part 1
// Design: ALU
// Group Number : 27
// E Numbers : E/18/077, E/18/227
// Names : Dharmarathne N.S., Mudalige D.H.
// Date: 09 January 2022

/**********************************************************************************/
// Define the FORWARD module
module forwardForALU(DATA2, RESULT);
	// Port declarations
	input [7:0] DATA2;
	output [7:0] RESULT;
	assign #1 RESULT=DATA2;
endmodule	// endmodule statement

/**********************************************************************************/
// Define the ADD module
module addForALU(DATA1, DATA2, RESULT);
	// Port declarations
	input [7:0] DATA1, DATA2;
	output [7:0] RESULT;
	assign #2 RESULT=DATA1 + DATA2;
endmodule	// endmodule statement

/**********************************************************************************/
// Define the AND module
module andForALU(DATA1, DATA2, RESULT);
	// Port declarations
	input [7:0] DATA1, DATA2;
	output [7:0] RESULT;
	assign #1 RESULT=DATA1 & DATA2;
endmodule	// endmodule statement

/**********************************************************************************/
// Define the OR module
module orForALU(DATA1, DATA2, RESULT);
	// Port declarations
	input [7:0] DATA1, DATA2;
	output [7:0] RESULT;
	assign #1 RESULT=DATA1 | DATA2;
endmodule	// endmodule statement

/**********************************************************************************/
// ALU 8-bit module 
module alu(DATA1, DATA2, SELECT, RESULT);
	// Port declarations, Declarations of wire & reg
	input [7:0] DATA1, DATA2;
	input [2:0] SELECT;
	output reg [7:0] RESULT;
	wire [7:0] RESULT_FOR_FORWARD, RESULT_FOR_ADD, RESULT_FOR_AND, RESULT_FOR_OR;
	
	// Instantiate modules
	forwardForALU forward_1(DATA2, RESULT_FOR_FORWARD);
	addForALU add_1(DATA1, DATA2, RESULT_FOR_ADD);
	andForALU and_1(DATA1, DATA2, RESULT_FOR_AND);
	orForALU or_1(DATA1, DATA2, RESULT_FOR_OR);

	// Select everytime DATA1, DATA2, SELECT updates
	always @(DATA1, DATA2, SELECT)
	begin
		// Select the function to implement using a case structure
		case(SELECT)
			3'b000:	//FORWARD
				assign RESULT=RESULT_FOR_FORWARD;
			3'b001:	//ADD
				assign RESULT=RESULT_FOR_ADD;
			3'b010:	//AND
				assign RESULT=RESULT_FOR_AND;
			3'b011:	//OR
				assign RESULT=RESULT_FOR_OR;
			default: RESULT=8'b00000000;	//DEFAULT
		endcase
	end
endmodule	// endmodule statement

Lab 5 - Building a Simple Processor/Part 3 - Integration & Control/mux2to1.v
// Computer Architecture (CO224) - Lab 05
// Design: 2 to 1 Multiplexer module
// Group Number : 27
// E Numbers : E/18/077, E/18/227
// Names : Dharmarathne N.S., Mudalige D.H.
// Date: 24/01/2022

module mux2to1(IN1, IN2, OUT, SELECT);
	input [7:0] IN1, IN2;
	input SELECT;
	output [7:0] OUT;
	assign OUT = (SELECT) ? IN1 : IN2;
endmodule

Lab 5 - Building a Simple Processor/Part 3 - Integration & Control/twos_comp.v
// Computer Architecture (CO224) - Lab 05
// Design: 2's Compliment Module
// Group Number : 27
// E Numbers : E/18/077, E/18/227
// Names : Dharmarathne N.S., Mudalige D.H.
// Date: 24/01/2022

module twos_comp (IN, COMPLIMENT);
	input [7:0] IN;
	output [7:0] COMPLIMENT;
	assign COMPLIMENT = ~IN + 8'b00000001;
endmodule

Lab 5 - Building a Simple Processor/Part 5 - Extended ISA/reg_file.v
// Computer Architecture (CO224) - Lab 05
// Design: Register File of Simple Processor
// Group Number : 27
// E Numbers : E/18/077, E/18/227
// Names : Dharmarathne N.S., Mudalige D.H.
// Date: 09 January 2022

module reg_file (
    input[7:0] IN,
    output[7:0] OUT1,
    output[7:0] OUT2,
    input[2:0] INADDRESS,
    input[2:0] OUT1ADDRESS,
    input[2:0] OUT2ADDRESS,
    input WRITE,
    input CLK,
    input RESET);

    // 8 element array of 8 bit registers
    reg [7:0] register[0:7];
    
    /********************************************************************/

    ///////////////// REGISTER READING OPERATIONS ////////////////////////
    // These assign statements are executed asynchrnously
    // (data is sent parallelly)

    // Note that, artificial delays of two time units for
    // register reading
    assign #2 OUT1 = register[OUT1ADDRESS];
    assign #2 OUT2 = register[OUT2ADDRESS];

    /*********************************************************************/


    /*********************************************************************/
    ///////////////// REGISTER WRITING OPERATIONS /////////////////////////
    
    integer i;
    // This always block triggered (synchronously) only for the  
    // positive edge of the clock pulse
    always @(posedge CLK) begin
        if (RESET) begin
            // This for loop is capable of resetting all register
            // values to zero when RESET signal is high

            #1  // Artificial delay of one time unit for resetting
            for (i = 0; i < 8; i = i + 1) begin
                register[i] <= 0;
            end
        end
        else begin
            // This else condition is used to write data contains inside IN
            // (when WRITE port is set high) to the required register 
            // specified by INADDRESS
            
            if (WRITE) #1 register[INADDRESS] <= IN;
            // Note that, artificial delays of one time units for
            // register writing
        end
    end
    /**********************************************************************/
    
	initial begin
        $dumpfile("cpu_wavedata_group27.vcd");
        for(i=0;i<8;++i)
            $dumpvars(1,register[i]);
    end

	initial begin
		#5
		$display("\t\t======================================================================");
		$display("\t\t\treg0\treg1\treg2\treg3\treg4\treg5\treg6\treg7");
		$display("\t\t======================================================================");
		$monitor($time,"\t%d\t%d\t%d\t%d\t%d\t%d\t%d\t%d", register[0],register[1],register[2],register[3],register[4],register[5],register[6],register[7]);
    end
	
endmodule

Lab 5 - Building a Simple Processor/Part 3 - Integration & Control/pc_adder.v
// Computer Architecture (CO224) - Lab 05
// Design: Dedicated Adder for PC Increment
// Group Number : 27
// E Numbers : E/18/077, E/18/227
// Names : Dharmarathne N.S., Mudalige D.H.
// Date: 24/01/2022

module pc_adder (
	input[31:0] PC,
	output[31:0] OFFSET);

	reg[31:0] OFFSET;

	always @(PC) begin
		// default offset(4 bit) is set 
		// with time delay of 1 time unit
		#1 OFFSET = 4;
	end

endmodule

Lab 5 - Building a Simple Processor/Part 3 - Integration & Control/pc.v
// Computer Architecture (CO224) - Lab 05
// Design: Program Count Module
// Group Number : 27
// E Numbers : E/18/077, E/18/227
// Names : Dharmarathne N.S., Mudalige D.H.
// Date: 24/01/2022

module pc (
	output[31:0] PCOUT,
    input RESET,
    input CLK);

	reg[31:0] PCOUT;
	wire [2:0] OFFSET;

	pc_adder myPCAdder (PCOUT, OFFSET);
	
	always @(posedge CLK) begin
		if (RESET) begin	// when resetting the pc,
			// write zero to pc value instead of the next pc value 
			// with a delay of 1 time unit
			#1 PCOUT = 0;  
		end
	end

	always @(posedge CLK) begin
		//pc write delay
	    #1 PCOUT = PCOUT + OFFSET;
	end

endmodule

Lab 5 - Building a Simple Processor/Part 3 - Integration & Control/cpu.v
// Computer Architecture (CO224) - Lab 05
// Design: Integrated CPU module for Simple Processor
// Author: Group 27
// Members: E/18/077 Nipun Dharmarathne
// 			E/18/227 Dinuka Mudalige
// Date: 20/01/2022

module cpu (
	output[31:0] PC, 
	input[31:0] INSTRUCTION, 
	input CLK, 
	input RESET);

	wire [7:0] REGOUT1, REGOUT2, COMPLIMENT, MUXCOMPOUT, MUXIMMOUT, ALURESULT;
	reg [7:0] IMMEDIATE, OPCODE;
	wire [2:0] ALUOP;
	reg [2:0] READREG1, READREG2, WRITEREG;
	wire MUXCOMPSELECT, MUXIMMSELECT, WRITEENABLE;
	wire [31:0] PC;

	always @(INSTRUCTION) begin
		READREG2 = INSTRUCTION[2:0];
		READREG1 = INSTRUCTION[10:8];
		WRITEREG = INSTRUCTION[18:16];
		IMMEDIATE = INSTRUCTION[7:0];
		#1 OPCODE = INSTRUCTION[31:24];
	end

	// assign PC = 32'b0000_0000_0000_0000_0000_0000_0000_0000;
	pc group27ProgramCounter (PC, RESET, CLK);
	reg_file group27RegisterFile (ALURESULT, REGOUT1, REGOUT2, WRITEREG, READREG1, READREG2, WRITEENABLE, CLK, RESET);
	twos_comp group27TwosCompliment (REGOUT2,COMPLIMENT);
	mux2to1 group27MUXCompliment (REGOUT2, COMPLIMENT, MUXCOMPOUT, MUXCOMPSELECT);
	mux2to1 group27MUXImmediate (IMMEDIATE, MUXCOMPOUT, MUXIMMOUT, MUXIMMSELECT);
	alu group27ALU (MUXIMMOUT, REGOUT1, ALUOP, ALURESULT);
	control_unit group27ControlUnit (OPCODE, ALUOP, WRITEENABLE, MUXCOMPSELECT, MUXIMMSELECT);
	
endmodule

Lab 5 - Building a Simple Processor/Part 3 - Integration & Control/cpu_tb.v
// Computer Architecture (CO224) - Lab 05
// Design: Testbench of Integrated CPU of Simple Processor
// Author: Isuru Nawinne

module cpu_tb;

    reg CLK, RESET;
    wire [31:0] PC;
    reg [31:0] INSTRUCTION;
    
    /* 
    ------------------------
     SIMPLE INSTRUCTION MEM
    ------------------------
    */

    // TODO: Initialize an array of registers (8x1024) named 'instr_mem' to be used as instruction memory
    reg [7:0 ] instr_mem[1023:0];
    
    // TODO: Create combinational logic to support CPU instruction fetching, given the Program Counter(PC) value 
    //       (make sure you include the delay for instruction fetching here)
    always @(PC) begin
       #2 INSTRUCTION = {instr_mem[PC+2'b11],instr_mem[PC+2'b10],instr_mem[PC+1'b1],instr_mem[PC]};
    end
    
    initial
    begin
        // Initialize instruction memory with the set of instructions you need execute on CPU
        
        // METHOD 1: manually loading instructions to instr_mem
        //{instr_mem[10'd3], instr_mem[10'd2], instr_mem[10'd1], instr_mem[10'd0]} = 32'b00000000000001000000000000000101;
        //{instr_mem[10'd7], instr_mem[10'd6], instr_mem[10'd5], instr_mem[10'd4]} = 32'b00000000000000100000000000001001;
        //{instr_mem[10'd11], instr_mem[10'd10], instr_mem[10'd9], instr_mem[10'd8]} = 32'b00000010000001100000010000000010;
        
        // METHOD 2: loading instr_mem content from instr_mem.mem file
        // $readmemb("programmer/instr_mem.mem", instr_mem);
	$readmemb("instr_mem.mem", instr_mem);
    end
    
    /* 
    -----
     CPU
    -----
    */
    cpu mycpu(PC, INSTRUCTION, CLK, RESET);

    initial
    begin
    
        // generate files needed to plot the waveform using GTKWave
        $dumpfile("cpu_wavedata_group27.vcd");
		$dumpvars(0, cpu_tb);
        
        CLK = 1'b0;
        // RESET = 1'b0;
        
        // TODO: Reset the CPU (by giving a pulse to RESET signal) to start the program execution
        RESET = 1'b1;
        #10;
        RESET = 1'b0;

        // finish simulation after some time
        #500
        $finish;
        
    end
    
    // clock signal generation
    always
        #4 CLK = ~CLK;
        

endmodule

Lab 5 - Building a Simple Processor/Part 3 - Integration & Control/cpu_wavedata_group27.vcd
$date
	Wed Jan 26 10:55:46 2022
$end
$version
	Icarus Verilog
$end
$timescale
	1s
$end
$scope module cpu_tb $end
$var wire 32 ! PC [31:0] $end
$var reg 1 " CLK $end
$var reg 32 # INSTRUCTION [31:0] $end
$var reg 1 $ RESET $end
$scope module mycpu $end
$var wire 1 " CLK $end
$var wire 32 % INSTRUCTION [31:0] $end
$var wire 1 $ RESET $end
$var wire 1 & WRITEENABLE $end
$var wire 8 ' REGOUT2 [7:0] $end
$var wire 8 ( REGOUT1 [7:0] $end
$var wire 32 ) PC [31:0] $end
$var wire 1 * MUXIMMSELECT $end
$var wire 8 + MUXIMMOUT [7:0] $end
$var wire 1 , MUXCOMPSELECT $end
$var wire 8 - MUXCOMPOUT [7:0] $end
$var wire 8 . COMPLIMENT [7:0] $end
$var wire 8 / ALURESULT [7:0] $end
$var wire 3 0 ALUOP [2:0] $end
$var reg 8 1 IMMEDIATE [7:0] $end
$var reg 8 2 OPCODE [7:0] $end
$var reg 3 3 READREG1 [2:0] $end
$var reg 3 4 READREG2 [2:0] $end
$var reg 3 5 WRITEREG [2:0] $end
$scope module group27ALU $end
$var wire 3 6 SELECT [2:0] $end
$var wire 8 7 RESULT_FOR_OR [7:0] $end
$var wire 8 8 RESULT_FOR_FORWARD [7:0] $end
$var wire 8 9 RESULT_FOR_AND [7:0] $end
$var wire 8 : RESULT_FOR_ADD [7:0] $end
$var wire 8 ; DATA2 [7:0] $end
$var wire 8 < DATA1 [7:0] $end
$var reg 8 = RESULT [7:0] $end
$scope module add_1 $end
$var wire 8 > RESULT [7:0] $end
$var wire 8 ? DATA2 [7:0] $end
$var wire 8 @ DATA1 [7:0] $end
$upscope $end
$scope module and_1 $end
$var wire 8 A RESULT [7:0] $end
$var wire 8 B DATA2 [7:0] $end
$var wire 8 C DATA1 [7:0] $end
$upscope $end
$scope module forward_1 $end
$var wire 8 D RESULT [7:0] $end
$var wire 8 E DATA2 [7:0] $end
$upscope $end
$scope module or_1 $end
$var wire 8 F RESULT [7:0] $end
$var wire 8 G DATA2 [7:0] $end
$var wire 8 H DATA1 [7:0] $end
$upscope $end
$upscope $end
$scope module group27ControlUnit $end
$var wire 8 I OPCODE [7:0] $end
$var reg 3 J ALUOP [2:0] $end
$var reg 1 , MUXCOMP $end
$var reg 1 * MUXIMM $end
$var reg 1 & WRITEENABLE $end
$upscope $end
$scope module group27MUXCompliment $end
$var wire 1 , SELECT $end
$var wire 8 K OUT [7:0] $end
$var wire 8 L IN2 [7:0] $end
$var wire 8 M IN1 [7:0] $end
$upscope $end
$scope module group27MUXImmediate $end
$var wire 8 N IN1 [7:0] $end
$var wire 8 O IN2 [7:0] $end
$var wire 1 * SELECT $end
$var wire 8 P OUT [7:0] $end
$upscope $end
$scope module group27ProgramCounter $end
$var wire 1 " CLK $end
$var wire 1 $ RESET $end
$var wire 3 Q OFFSET [2:0] $end
$var reg 32 R PCOUT [31:0] $end
$scope module myPCAdder $end
$var wire 32 S PC [31:0] $end
$var reg 32 T OFFSET [31:0] $end
$upscope $end
$upscope $end
$scope module group27RegisterFile $end
$var wire 1 " CLK $end
$var wire 8 U IN [7:0] $end
$var wire 3 V INADDRESS [2:0] $end
$var wire 8 W OUT1 [7:0] $end
$var wire 3 X OUT1ADDRESS [2:0] $end
$var wire 8 Y OUT2 [7:0] $end
$var wire 3 Z OUT2ADDRESS [2:0] $end
$var wire 1 $ RESET $end
$var wire 1 & WRITE $end
$var integer 32 [ i [31:0] $end
$upscope $end
$scope module group27TwosCompliment $end
$var wire 8 \ IN [7:0] $end
$var wire 8 ] COMPLIMENT [7:0] $end
$upscope $end
$upscope $end
$upscope $end
$enddefinitions $end
#0
$dumpvars
bx ]
bx \
bx [
bx Z
bx Y
bx X
bx W
bx V
bx U
bx T
bx S
bx R
bx Q
bx P
bx O
bx N
bx M
bx L
bx K
bx J
bx I
bx H
bx G
bx F
bx E
bx D
bx C
bx B
bx A
bx @
bx ?
bx >
bx =
bx <
bx ;
bx :
bx 9
bx 8
bx 7
bx 6
bx 5
bx 4
bx 3
bx 2
bx 1
bx 0
bx /
bx .
bx -
x,
bx +
x*
bx )
bx (
bx '
x&
bx %
1$
bx #
0"
bx !
$end
#4
1"
#5
b0 !
b0 )
b0 R
b0 S
b1000 [
#6
b100 Q
b100 T
#7
b101 1
b101 N
b100 5
b100 V
b0 3
b0 X
b101 4
b101 Z
b1000000000000000101 #
b1000000000000000101 %
#8
b101 +
b101 <
b101 @
b101 C
b101 H
b101 P
1&
1*
0,
b0 0
b0 6
b0 J
b0 2
b0 I
0"
#9
b0 -
b0 K
b0 O
b0 .
b0 L
b0 ]
bx1x1 7
bx1x1 F
b0x0x 9
b0x0x A
b0 (
b0 ;
b0 ?
b0 B
b0 E
b0 G
b0 W
b0 '
b0 M
b0 Y
b0 \
#10
b101 7
b101 F
b0 9
b0 A
b0 /
b0 =
b0 U
b0 8
b0 D
0$
#11
b101 :
b101 >
#12
1"
#13
b100 !
b100 )
b100 R
b100 S
#15
b1001 +
b1001 <
b1001 @
b1001 C
b1001 H
b1001 P
b1001 1
b1001 N
b10 5
b10 V
b1 4
b1 Z
b100000000000001001 #
b100000000000001001 %
#16
b1001 7
b1001 F
0"
#17
b1001 :
b1001 >
#20
1"
#21
b1000 !
b1000 )
b1000 R
b1000 S
#23
b10 +
b10 <
b10 @
b10 C
b10 H
b10 P
b10 1
b10 N
b110 5
b110 V
b100 3
b100 X
b10 4
b10 Z
b10000001100000010000000010 #
b10000001100000010000000010 %
#24
b1001 /
b1001 =
b1001 U
b1 0
b1 6
b1 J
b10 7
b10 F
b10 2
b10 I
0"
#25
b10 /
b10 =
b10 U
b10 :
b10 >
#28
1"
#29
b1100 !
b1100 )
b1100 R
b1100 S
#31
b110 +
b110 <
b110 @
b110 C
b110 H
b110 P
b110 1
b110 N
b0 5
b0 V
b0 3
b0 X
b110 4
b110 Z
b1000000000000000000000110 #
b1000000000000000000000110 %
#32
b0 /
b0 =
b0 U
b0 0
b0 6
b0 J
b110 7
b110 F
b1 2
b1 I
0"
#33
b11111110 -
b11111110 K
b11111110 O
b11111110 .
b11111110 L
b11111110 ]
b110 :
b110 >
b10 '
b10 M
b10 Y
b10 \
#36
1"
#37
b10000 !
b10000 )
b10000 R
b10000 S
#39
b1 +
b1 <
b1 @
b1 C
b1 H
b1 P
b1 1
b1 N
b1 5
b1 V
b1 4
b1 Z
b10000000000000001 #
b10000000000000001 %
#40
b1 7
b1 F
b0 2
b0 I
0"
#41
b0 -
b0 K
b0 O
b0 .
b0 L
b0 ]
b1 :
b1 >
b0 '
b0 M
b0 Y
b0 \
#44
1"
#45
b10100 !
b10100 )
b10100 R
b10100 S
#47
b10 5
b10 V
b10 3
b10 X
b10000000100000001000000001 #
b10000000100000001000000001 %
#48
b1 /
b1 =
b1 U
b1 0
b1 6
b1 J
b10 2
b10 I
0"
#52
1"
#53
b11000 !
b11000 )
b11000 R
b11000 S
#55
bx +
bx <
bx @
bx C
bx H
bx P
bx 1
bx N
bx 5
bx V
bx 3
bx X
bx 4
bx Z
b1 (
b1 ;
b1 ?
b1 B
b1 E
b1 G
b1 W
bx #
bx %
#56
b0 +
b0 <
b0 @
b0 C
b0 H
b0 P
0&
0*
bx1 7
bx1 F
b0x 9
b0x A
bx 2
bx I
b1 8
b1 D
0"
#57
bx +
bx <
bx @
bx C
bx H
bx P
bx -
bx K
bx O
bx .
bx L
bx ]
b1 7
b1 F
b0 9
b0 A
bx (
bx ;
bx ?
bx B
bx E
bx G
bx W
bx '
bx M
bx Y
bx \
#58
bx 9
bx A
bx 7
bx F
bx 8
bx D
#59
bx /
bx =
bx U
bx :
bx >
#60
1"
#61
b11100 !
b11100 )
b11100 R
b11100 S
#64
0"
#68
1"
#69
b100000 !
b100000 )
b100000 R
b100000 S
#72
0"
#76
1"
#77
b100100 !
b100100 )
b100100 R
b100100 S
#80
0"
#84
1"
#85
b101000 !
b101000 )
b101000 R
b101000 S
#88
0"
#92
1"
#93
b101100 !
b101100 )
b101100 R
b101100 S
#96
0"
#100
1"
#101
b110000 !
b110000 )
b110000 R
b110000 S
#104
0"
#108
1"
#109
b110100 !
b110100 )
b110100 R
b110100 S
#112
0"
#116
1"
#117
b111000 !
b111000 )
b111000 R
b111000 S
#120
0"
#124
1"
#125
b111100 !
b111100 )
b111100 R
b111100 S
#128
0"
#132
1"
#133
b1000000 !
b1000000 )
b1000000 R
b1000000 S
#136
0"
#140
1"
#141
b1000100 !
b1000100 )
b1000100 R
b1000100 S
#144
0"
#148
1"
#149
b1001000 !
b1001000 )
b1001000 R
b1001000 S
#152
0"
#156
1"
#157
b1001100 !
b1001100 )
b1001100 R
b1001100 S
#160
0"
#164
1"
#165
b1010000 !
b1010000 )
b1010000 R
b1010000 S
#168
0"
#172
1"
#173
b1010100 !
b1010100 )
b1010100 R
b1010100 S
#176
0"
#180
1"
#181
b1011000 !
b1011000 )
b1011000 R
b1011000 S
#184
0"
#188
1"
#189
b1011100 !
b1011100 )
b1011100 R
b1011100 S
#192
0"
#196
1"
#197
b1100000 !
b1100000 )
b1100000 R
b1100000 S
#200
0"
#204
1"
#205
b1100100 !
b1100100 )
b1100100 R
b1100100 S
#208
0"
#212
1"
#213
b1101000 !
b1101000 )
b1101000 R
b1101000 S
#216
0"
#220
1"
#221
b1101100 !
b1101100 )
b1101100 R
b1101100 S
#224
0"
#228
1"
#229
b1110000 !
b1110000 )
b1110000 R
b1110000 S
#232
0"
#236
1"
#237
b1110100 !
b1110100 )
b1110100 R
b1110100 S
#240
0"
#244
1"
#245
b1111000 !
b1111000 )
b1111000 R
b1111000 S
#248
0"
#252
1"
#253
b1111100 !
b1111100 )
b1111100 R
b1111100 S
#256
0"
#260
1"
#261
b10000000 !
b10000000 )
b10000000 R
b10000000 S
#264
0"
#268
1"
#269
b10000100 !
b10000100 )
b10000100 R
b10000100 S
#272
0"
#276
1"
#277
b10001000 !
b10001000 )
b10001000 R
b10001000 S
#280
0"
#284
1"
#285
b10001100 !
b10001100 )
b10001100 R
b10001100 S
#288
0"
#292
1"
#293
b10010000 !
b10010000 )
b10010000 R
b10010000 S
#296
0"
#300
1"
#301
b10010100 !
b10010100 )
b10010100 R
b10010100 S
#304
0"
#308
1"
#309
b10011000 !
b10011000 )
b10011000 R
b10011000 S
#312
0"
#316
1"
#317
b10011100 !
b10011100 )
b10011100 R
b10011100 S
#320
0"
#324
1"
#325
b10100000 !
b10100000 )
b10100000 R
b10100000 S
#328
0"
#332
1"
#333
b10100100 !
b10100100 )
b10100100 R
b10100100 S
#336
0"
#340
1"
#341
b10101000 !
b10101000 )
b10101000 R
b10101000 S
#344
0"
#348
1"
#349
b10101100 !
b10101100 )
b10101100 R
b10101100 S
#352
0"
#356
1"
#357
b10110000 !
b10110000 )
b10110000 R
b10110000 S
#360
0"
#364
1"
#365
b10110100 !
b10110100 )
b10110100 R
b10110100 S
#368
0"
#372
1"
#373
b10111000 !
b10111000 )
b10111000 R
b10111000 S
#376
0"
#380
1"
#381
b10111100 !
b10111100 )
b10111100 R
b10111100 S
#384
0"
#388
1"
#389
b11000000 !
b11000000 )
b11000000 R
b11000000 S
#392
0"
#396
1"
#397
b11000100 !
b11000100 )
b11000100 R
b11000100 S
#400
0"
#404
1"
#405
b11001000 !
b11001000 )
b11001000 R
b11001000 S
#408
0"
#412
1"
#413
b11001100 !
b11001100 )
b11001100 R
b11001100 S
#416
0"
#420
1"
#421
b11010000 !
b11010000 )
b11010000 R
b11010000 S
#424
0"
#428
1"
#429
b11010100 !
b11010100 )
b11010100 R
b11010100 S
#432
0"
#436
1"
#437
b11011000 !
b11011000 )
b11011000 R
b11011000 S
#440
0"
#444
1"
#445
b11011100 !
b11011100 )
b11011100 R
b11011100 S
#448
0"
#452
1"
#453
b11100000 !
b11100000 )
b11100000 R
b11100000 S
#456
0"
#460
1"
#461
b11100100 !
b11100100 )
b11100100 R
b11100100 S
#464
0"
#468
1"
#469
b11101000 !
b11101000 )
b11101000 R
b11101000 S
#472
0"
#476
1"
#477
b11101100 !
b11101100 )
b11101100 R
b11101100 S
#480
0"
#484
1"
#485
b11110000 !
b11110000 )
b11110000 R
b11110000 S
#488
0"
#492
1"
#493
b11110100 !
b11110100 )
b11110100 R
b11110100 S
#496
0"
#500
1"
#501
b11111000 !
b11111000 )
b11111000 R
b11111000 S
#504
0"
#508
1"
#509
b11111100 !
b11111100 )
b11111100 R
b11111100 S
